payhere_python/__init__.py
payhere_python/exceptions.py
payhere_python/main.py
payhere_python/response.py
payhere_python/setup.py
payhere_python/utils.py
payhere_python-1.0.3.dist-info/licenses/LICENSE
payhere_python-1.0.3.dist-info/METADATA
payhere_python-1.0.3.dist-info/WHEEL
payhere_python-1.0.3.dist-info/top_level.txt
payhere_python-1.0.3.dist-info/RECORD
