Metadata-Version: 2.4
Name: payhere-python
Version: 1.0.3
Summary: Unofficial Python SDK for PayHere Payment Gateway
Author: Kavindu Harshitha
Author-email: Kavindu Harshitha <kavindu@apexkv.com>
License: GNU GENERAL PUBLIC LICENSE
Project-URL: Homepage, https://github.com/apexkv/payhere-python
Project-URL: Repository, https://github.com/apexkv/payhere-python
Project-URL: Issues, https://github.com/apexkv/payhere-python/issues
Keywords: payhere,payment,sdk,sri-lanka,python
Classifier: Programming Language :: Python :: 3
Classifier: License :: OSI Approved :: GNU General Public License v3 (GPLv3)
Classifier: Operating System :: OS Independent
Requires-Python: >=3.9
License-File: LICENSE
Requires-Dist: requests
Requires-Dist: pydantic
Dynamic: author
Dynamic: license-file
Dynamic: requires-python
